MANIFEST.in
README.rst
setup.py
bin/VERSION
bin/__init__.py
bin/dsms_cli.py
dsms_cli.egg-info/PKG-INFO
dsms_cli.egg-info/SOURCES.txt
dsms_cli.egg-info/dependency_links.txt
dsms_cli.egg-info/entry_points.txt
dsms_cli.egg-info/pbr.json
dsms_cli.egg-info/requires.txt
dsms_cli.egg-info/top_level.txt
dsms_cmd/__init__.py
dsms_cmd/dsms_cmd.py
dsms_cmd/templates/standard.j2