Metadata-Version: 1.1
Name: dsms-cli
Version: 1.1.8
Summary: DSMS CLI tool
Home-page: https://bitbucket.org/dsms/dsms_report_cli
Author: Chris Horsley
Author-email: chris.horsley@csirtfoundry.com
License: Apache 2.0
Keywords: DSMS
Platform: UNKNOWN
Classifier: Development Status :: 3 - Alpha
Classifier: Intended Audience :: Developers
Classifier: License :: OSI Approved :: Apache Software License
Classifier: Programming Language :: Python :: 2.7
